SevenSeg.v
module SevenSeg(
 
    //////////// SEG7 //////////
    output           [7:0]      H,
 
    //////////// KEY //////////
    input            [7:0]     NUM
    
);
 
    reg [7:0] value;
 
//takes decimal number and converts to binary for HEX display based on logic 0 = on, logic 1 = off for each segment
//if NUM = 'd88 is blank(pos)
//if NUM = 'd99 is minus sign
    always @(NUM)
        begin
            case(NUM)
                8'd0: value = 8'b11000000;
                8'd1: value = 8'b11111001;
                8'd2: value = 8'b10100100;
                8'd3: value = 8'b10110000;
                8'd4: value = 8'b10011001;
                8'd5: value = 8'b10010010;
                8'd6: value = 8'b10000010;
                8'd7: value = 8'b11111000;
                8'd8: value = 8'b10000000;
                8'd9: value = 8'b10011000;
                8'd10: value = 8'b10001000; 
                8'd11: value = 8'b10000011;
                8'd12: value = 8'b11000110;
                8'd13: value = 8'b10100001;
                8'd14: value = 8'b10000110;
                8'd15: value = 8'b10001110;
 
                8'd88: value = 8'b11111111;
                8'd99: value = 8'b10111111;
                default: value = 8'b00000000;
            endcase
        end
 
 
    //the HEX display passed is given whatever value determined above
    assign H[7:0] = value;
 
 
endmodule

OL.v
module OL(
    input [2:0] CurrentState,
    input clk,
    input reset_n,
    input [1:0] SW,
    input [1:0] K,
    //input turn_side,
    output [7:0] HEX0,
    output reg [2:0] LEDR_L,
    output reg [2:0] LEDR_R
);

    parameter IDLE = 3'b000;
	parameter HAZARDS = 3'b001;
	parameter TURN_LEFT = 3'b010;
	parameter TURN_RIGHT = 3'b011;

    reg hazard_r = 1'b0;
    reg [1:0] turn_cnt = 2'b00;

    always @(posedge clk, negedge reset_n)
        begin
            if(reset_n == 0)
                begin
                    LEDR_R <= 3'b000;
                    LEDR_L <= 3'b000;
                end
            else
                begin
                    case(CurrentState)
                        HAZARDS: begin
                                hazard_r <= ~hazard_r;
                                if(hazard_r == 1'b0)
                                    begin
                                        LEDR_L <= 3'b000;
                                        LEDR_R <= 3'b000;
                                    end
                                else if(hazard_r == 1'b1)
                                    begin
                                        LEDR_L <= 3'b111;
                                        LEDR_R <= 3'b111;
                                    end
                            end
                        TURN_LEFT: begin
                                LEDR_R <= 3'b000;
                                if(turn_cnt == 2'b11)
                                    turn_cnt <= 2'b00;
                                else
                                    turn_cnt <= turn_cnt + 2'b01;
                                case(turn_cnt)
                                2'b01: LEDR_L <= 3'b001;
                                2'b10: LEDR_L <= 3'b011;
                                2'b11: LEDR_L <= 3'b111;
                                default: LEDR_L <= 3'b000;
                                endcase
                            end
                        TURN_RIGHT: begin
                                LEDR_L <= 3'b000;
                                if(turn_cnt == 2'b11)
                                    turn_cnt <= 2'b00;
                                else
                                    turn_cnt <= turn_cnt + 2'b01;
                                case(turn_cnt)
                                2'b01: LEDR_R <= 3'b100;
                                2'b10: LEDR_R <= 3'b110;
                                2'b11: LEDR_R <= 3'b111;
                                default: LEDR_R <= 3'b000;
                                endcase  
                            end
                        default: begin
                                LEDR_L <= 3'b000;
                                LEDR_R <= 3'b000;
                            end
            endcase
            end 
        end


    reg[7:0] num;

    always @(CurrentState)
        num <= CurrentState;

    SevenSeg S0(.H(HEX0), .NUM(num));

endmodule

NSL.v
module NSL(
	input [2:0] CurrentState,
    input clk,
    input [1:0] SW,
    input turn_side_r,
	output [2:0] NextState, 
    input [1:0] K
);

    parameter IDLE = 3'b000;
	parameter HAZARDS = 3'b001;
	parameter TURN_LEFT = 3'b010;
	parameter TURN_RIGHT = 3'b011;

    reg [2:0] NextState_temp;

    always @(CurrentState)
        begin
            if(SW[0] == 1)
                begin
                    NextState_temp <= HAZARDS; //3'b001; //hazards
                end
            else if(SW[1] == 1)
                begin
                    if(turn_side_r == 0)
                        NextState_temp <= TURN_LEFT; //3'b010; //turn left
                    else if(turn_side_r == 1)
                        NextState_temp <= TURN_RIGHT; //3'b100; //turn right
                end
            else
                NextState_temp <= IDLE; //3'b000; //idle
        end
    
    assign NextState = NextState_temp;
    
endmodule

CSL.v
module CSL(
	input clk,
	input reset_n,
	input [2:0] NextState,
	output reg [2:0] CurrentState,
    input [9:0] SW,
    input [1:0] K
);

    parameter IDLE = 3'b000;
	parameter HAZARDS = 3'b001;
	parameter TURN_LEFT = 3'b010;
	parameter TURN_RIGHT = 3'b011;

    always @(posedge clk, negedge reset_n)
        if(reset_n == 0)
            CurrentState = IDLE; //3'b000;
        else
            CurrentState = NextState;

endmodule

clock_divider.v
module clock_divider(

	//////////// CLOCK //////////
	input 		          		clk,
    input                       reset_n,
    output                      slower_clk      //calculate correct size!                
);

    parameter clk_div = 0;

    reg [23:0] div_cntr; //calculate correct size!
    reg slw_clk;

    always @(posedge clk, negedge reset_n)
        begin
            if(reset_n == 0)
                begin
                    div_cntr <= 0;
                    slw_clk <= 0;
                end
            else if(div_cntr == clk_div - 1)
                begin
                    div_cntr <= 0;
                    slw_clk <= ~slw_clk;
                end
            else
                begin
                    div_cntr <= div_cntr + 1;
                end
        end

    assign slower_clk = slw_clk;

endmodule

Lab3.v

//=======================================================
//  This code is generated by Terasic System Builder
//=======================================================

module Lab3(

	//////////// CLOCK //////////
	input 		          		ADC_CLK_10,
	input 		          		MAX10_CLK1_50,
	input 		          		MAX10_CLK2_50,

	//////////// SEG7 //////////
	output		     [7:0]		HEX0,
	output		     [7:0]		HEX1,
	output		     [7:0]		HEX2,
	output		     [7:0]		HEX3,
	output		     [7:0]		HEX4,
	output		     [7:0]		HEX5,

	//////////// KEY //////////
	input 		     [1:0]		KEY,

	//////////// LED //////////
	output		     [9:0]		LEDR,

	//////////// SW //////////
	input 		     [9:0]		SW
);

	assign LEDR[6:3] = 4'b0000;

	//currently ALL seven segs blanked, need to use some to display state of state machine
	//SevenSeg U0(.H(HEX0), .NUM(8'd88));
	SevenSeg U1(.H(HEX1), .NUM(8'd88));
	SevenSeg U2(.H(HEX2), .NUM(8'd88));
	SevenSeg U3(.H(HEX3), .NUM(8'd88));
	SevenSeg U4(.H(HEX4), .NUM(8'd88));
	SevenSeg U5(.H(HEX5), .NUM(8'd88));

	reg reset_latch = 1'b0;

	always @(negedge KEY[0])
		begin
			reset_latch <= ~reset_latch;
		end

	wire s_clk;

	clock_divider #(1_000_000) C0(.clk(ADC_CLK_10), .reset_n(reset_latch), .slower_clk(s_clk));


	reg turn_side_r = 1'b0;

	always @(negedge KEY[1])
		begin
			turn_side_r <= ~turn_side_r;
		end


	parameter IDLE = 3'b000;
	parameter HAZARDS = 3'b001;
	parameter TURN_LEFT = 3'b010;
	parameter TURN_RIGHT = 3'b011;

	wire [2:0] CurrentState;
	wire [2:0] NextState;

	CSL S0(.clk(s_clk), .reset_n(reset_latch), .NextState(NextState), .CurrentState(CurrentState));
	NSL N0(.CurrentState(CurrentState), .SW(SW[1:0]), .turn_side_r(turn_side_r), .NextState(NextState));
	OL O0(.CurrentState(CurrentState), .clk(s_clk), .reset_n(reset_latch), .SW(SW[1:0]), .HEX0(HEX0), .LEDR_L(LEDR[9:7]), .LEDR_R(LEDR[2:0]));

endmodule

tb_Lab3.v
`timescale 1 ns / 100 ps

module tb_Lab3();

    reg clk;
    reg Rn;
    wire [7:0] HEX0;
    wire [7:0] HEX1;
    wire [7:0] HEX3;
    wire [7:0] HEX2;
    wire [7:0] HEX4;
    wire [7:0] HEX5;
    wire [1:0] K;
    reg [9:0] sw = 9'b0;
    wire [9:0] led;

    Lab3 L0(
        .ADC_CLK_10(clk),
        .HEX0(HEX0),
        .HEX1(HEX1),
        .HEX2(HEX2),
        .HEX3(HEX3),
        .HEX4(HEX4),
        .HEX5(HEX5),
        .KEY(K),
        .LEDR(led),
        .SW(sw)
    );

    initial
        begin
            clk = 1'b0;
            Rn = 1'b0;
        #10 Rn = 1'b1;
        end

    always
        #5 clk = ~clk;
         sw = ~sw;

    initial
        begin
            $dumpfile("output.vcd");
            $dumpvars;
            $display("Starting simulation");
        end   

    initial
        begin
        $monitor("%d,\t%b,\t%b,\t%d", $time, clk, Rn, led, HEX0);        
        end

        initial
            begin
            $display("Simulation ended.");
            #1300 $finish;
            end

endmodule

output.vcd
$date
	Tue Dec 10 21:44:45 2019
$end
$version
	Icarus Verilog
$end
$timescale
	100ps
$end
$scope module tb_Lab3 $end
$var wire 10 ! led [9:0] $end
$var wire 8 " HEX5 [7:0] $end
$var wire 8 # HEX4 [7:0] $end
$var wire 8 $ HEX3 [7:0] $end
$var wire 8 % HEX2 [7:0] $end
$var wire 8 & HEX1 [7:0] $end
$var wire 8 ' HEX0 [7:0] $end
$var reg 2 ( K [1:0] $end
$var reg 1 ) Rn $end
$var reg 1 * clk $end
$var reg 10 + sw [9:0] $end
$scope module L0 $end
$var wire 1 * ADC_CLK_10 $end
$var wire 2 , KEY [1:0] $end
$var wire 1 - MAX10_CLK1_50 $end
$var wire 1 . MAX10_CLK2_50 $end
$var wire 10 / SW [9:0] $end
$var wire 1 0 s_clk $end
$var wire 3 1 NextState [2:0] $end
$var wire 10 2 LEDR [9:0] $end
$var wire 8 3 HEX5 [7:0] $end
$var wire 8 4 HEX4 [7:0] $end
$var wire 8 5 HEX3 [7:0] $end
$var wire 8 6 HEX2 [7:0] $end
$var wire 8 7 HEX1 [7:0] $end
$var wire 8 8 HEX0 [7:0] $end
$var wire 3 9 CurrentState [2:0] $end
$var reg 1 : reset_latch $end
$var reg 1 ; turn_side_r $end
$scope module C0 $end
$var wire 1 * clk $end
$var wire 1 : reset_n $end
$var wire 1 0 slower_clk $end
$var reg 24 < div_cntr [23:0] $end
$var reg 1 = slw_clk $end
$upscope $end
$scope module N0 $end
$var wire 2 > K [1:0] $end
$var wire 3 ? NextState [2:0] $end
$var wire 2 @ SW [1:0] $end
$var wire 1 ; turn_side_r $end
$var wire 3 A CurrentState [2:0] $end
$var reg 3 B NextState_temp [2:0] $end
$upscope $end
$scope module O0 $end
$var wire 2 C K [1:0] $end
$var wire 2 D SW [1:0] $end
$var wire 1 0 clk $end
$var wire 1 : reset_n $end
$var wire 8 E HEX0 [7:0] $end
$var wire 3 F CurrentState [2:0] $end
$var reg 3 G LEDR_L [2:0] $end
$var reg 3 H LEDR_R [2:0] $end
$var reg 1 I hazard_r $end
$var reg 8 J num [7:0] $end
$var reg 2 K turn_cnt [1:0] $end
$scope module S0 $end
$var wire 8 L H [7:0] $end
$var wire 8 M NUM [7:0] $end
$var reg 8 N value [7:0] $end
$upscope $end
$upscope $end
$scope module S0 $end
$var wire 2 O K [1:0] $end
$var wire 3 P NextState [2:0] $end
$var wire 10 Q SW [9:0] $end
$var wire 1 0 clk $end
$var wire 1 : reset_n $end
$var reg 3 R CurrentState [2:0] $end
$upscope $end
$scope module U1 $end
$var wire 8 S H [7:0] $end
$var wire 8 T NUM [7:0] $end
$var reg 8 U value [7:0] $end
$upscope $end
$scope module U2 $end
$var wire 8 V H [7:0] $end
$var wire 8 W NUM [7:0] $end
$var reg 8 X value [7:0] $end
$upscope $end
$scope module U3 $end
$var wire 8 Y H [7:0] $end
$var wire 8 Z NUM [7:0] $end
$var reg 8 [ value [7:0] $end
$upscope $end
$scope module U4 $end
$var wire 8 \ H [7:0] $end
$var wire 8 ] NUM [7:0] $end
$var reg 8 ^ value [7:0] $end
$upscope $end
$scope module U5 $end
$var wire 8 _ H [7:0] $end
$var wire 8 ` NUM [7:0] $end
$var reg 8 a value [7:0] $end
$upscope $end
$upscope $end
$upscope $end
$enddefinitions $end
#0
$dumpvars
b11111111 a
b1011000 `
b11111111 _
b11111111 ^
b1011000 ]
b11111111 \
b11111111 [
b1011000 Z
b11111111 Y
b11111111 X
b1011000 W
b11111111 V
b11111111 U
b1011000 T
b11111111 S
b0 R
b0 Q
b0 P
b0 O
b11000000 N
b0 M
b11000000 L
b0 K
b0 J
0I
b0 H
b0 G
b0 F
b11000000 E
b0 D
b0 C
b0 B
b0 A
b0 @
b0 ?
b0 >
0=
b0 <
1;
1:
b0 9
b11000000 8
b11111111 7
b11111111 6
b11111111 5
b11111111 4
b11111111 3
b0 2
b0 1
00
b0 /
z.
z-
b0 ,
b0 +
0*
0)
b0 (
b11000000 '
b11111111 &
b11111111 %
b11111111 $
b11111111 #
b11111111 "
b0 !
$end
#50
b1 <
1*
#100
b1 1
b1 ?
b1 P
b1 B
b1 @
b1 D
0*
b1 +
b1 /
b1 Q
1)
#150
b10 <
1*
#200
b11111001 '
b11111001 8
b11111001 E
b11111001 L
b11111001 N
b11 1
b11 ?
b11 P
b11 B
1I
b1 J
b1 M
b10 @
b10 D
b1 9
b1 A
b1 F
b1 R
0*
b10 +
b10 /
b10 Q
#250
b11 <
1*
#300
0*
#350
b100 <
1*
#400
b10110000 '
b10110000 8
b10110000 E
b10110000 L
b10110000 N
b11 J
b11 M
b1 K
b11 9
b11 A
b11 F
b11 R
0*
b10 (
b10 ,
b10 >
b10 C
b10 O
#450
b101 <
1*
#500
b1 1
b1 ?
b1 P
b1 B
b100 !
b100 2
b100 H
b10 K
b11 @
b11 D
0*
b11 +
b11 /
b11 Q
#550
b110 <
1*
#600
b11111001 '
b11111001 8
b11111001 E
b11111001 L
b11111001 N
b0 1
b0 ?
b0 P
b0 B
b111 H
b1110000111 !
b1110000111 2
b111 G
0I
b1 J
b1 M
b0 @
b0 D
b1 9
b1 A
b1 F
b1 R
0*
b0 +
b0 /
b0 Q
#650
b111 <
1*
#700
b11000000 '
b11000000 8
b11000000 E
b11000000 L
b11000000 N
b11 1
b11 ?
b11 P
b11 B
b0 H
b0 !
b0 2
b0 G
b0 J
b0 M
b10 @
b10 D
b0 9
b0 A
b0 F
b0 R
0*
b10 +
b10 /
b10 Q
#750
b1000 <
1*
#800
0*
#850
b1001 <
1*
#900
b10110000 '
b10110000 8
b10110000 E
b10110000 L
b10110000 N
0;
b11 J
b11 M
b110 !
b110 2
b110 H
b11 K
b11 9
b11 A
b11 F
b11 R
0*
b0 (
b0 ,
b0 >
b0 C
b0 O
#950
b1010 <
1*
#1000
0*
#1050
b1011 <
1*
#1100
0*
#1150
b1100 <
1*
#1200
0*
#1250
b1101 <
1*
#1300
0*
#1350
b1110 <
1*
#1400
0*
#1450
b1111 <
1*
#1500
0*
#1550
b10000 <
1*
#1600
0*
#1650
b10001 <
1*
#1700
0*
#1750
b10010 <
1*
#1800
0*
#1850
b10011 <
1*
#1900
0*
#1950
b10100 <
1*
#2000
0*
#2050
b10101 <
1*
#2100
0*
#2150
b10110 <
1*
#2200
0*
#2250
b10111 <
1*
#2300
0*
#2350
b11000 <
1*
#2400
0*
#2450
b11001 <
1*
#2500
0*
#2550
b11010 <
1*
#2600
0*
#2650
b11011 <
1*
#2700
0*
#2750
b11100 <
1*
#2800
0*
#2850
b11101 <
1*
#2900
0*
#2950
b11110 <
1*
#3000
0*
#3050
b11111 <
1*
#3100
0*
#3150
b100000 <
1*
#3200
0*
#3250
b100001 <
1*
#3300
0*
#3350
b100010 <
1*
#3400
0*
#3450
b100011 <
1*
#3500
0*
#3550
b100100 <
1*
#3600
0*
#3650
b100101 <
1*
#3700
0*
#3750
b100110 <
1*
#3800
0*
#3850
b100111 <
1*
#3900
0*
#3950
b101000 <
1*
#4000
0*
#4050
b101001 <
1*
#4100
0*
#4150
b101010 <
1*
#4200
0*
#4250
b101011 <
1*
#4300
0*
#4350
b101100 <
1*
#4400
0*
#4450
b101101 <
1*
#4500
0*
#4550
b101110 <
1*
#4600
0*
#4650
b101111 <
1*
#4700
0*
#4750
b110000 <
1*
#4800
0*
#4850
b110001 <
1*
#4900
0*
#4950
b110010 <
1*
#5000
0*
#5050
b110011 <
1*
#5100
0*
#5150
b110100 <
1*
#5200
0*
#5250
b110101 <
1*
#5300
0*
#5350
b110110 <
1*
#5400
0*
#5450
b110111 <
1*
#5500
0*
#5550
b111000 <
1*
#5600
0*
#5650
b111001 <
1*
#5700
0*
#5750
b111010 <
1*
#5800
0*
#5850
b111011 <
1*
#5900
0*
#5950
b111100 <
1*
#6000
0*
#6050
b111101 <
1*
#6100
0*
#6150
b111110 <
1*
#6200
0*
#6250
b111111 <
1*
#6300
0*
#6350
b1000000 <
1*
#6400
0*
#6450
b1000001 <
1*
#6500
0*
#6550
b1000010 <
1*
#6600
0*
#6650
b1000011 <
1*
#6700
0*
#6750
b1000100 <
1*
#6800
0*
#6850
b1000101 <
1*
#6900
0*
#6950
b1000110 <
1*
#7000
0*
#7050
b1000111 <
1*
#7100
0*
#7150
b1001000 <
1*
#7200
0*
#7250
b1001001 <
1*
#7300
0*
#7350
b1001010 <
1*
#7400
0*
#7450
b1001011 <
1*
#7500
0*
#7550
b1001100 <
1*
#7600
0*
#7650
b1001101 <
1*
#7700
0*
#7750
b1001110 <
1*
#7800
0*
#7850
b1001111 <
1*
#7900
0*
#7950
b1010000 <
1*
#8000
0*
#8050
b1010001 <
1*
#8100
0*
#8150
b1010010 <
1*
#8200
0*
#8250
b1010011 <
1*
#8300
0*
#8350
b1010100 <
1*
#8400
0*
#8450
b1010101 <
1*
#8500
0*
#8550
b1010110 <
1*
#8600
0*
#8650
b1010111 <
1*
#8700
0*
#8750
b1011000 <
1*
#8800
0*
#8850
b1011001 <
1*
#8900
0*
#8950
b1011010 <
1*
#9000
0*
#9050
b1011011 <
1*
#9100
0*
#9150
b1011100 <
1*
#9200
0*
#9250
b1011101 <
1*
#9300
0*
#9350
b1011110 <
1*
#9400
0*
#9450
b1011111 <
1*
#9500
0*
#9550
b1100000 <
1*
#9600
0*
#9650
b1100001 <
1*
#9700
0*
#9750
b1100010 <
1*
#9800
0*
#9850
b1100011 <
1*
#9900
0*
#9950
b1100100 <
1*
#10000
0*
#10050
b1100101 <
1*
#10100
0*
#10150
b1100110 <
1*
#10200
0*
#10250
b1100111 <
1*
#10300
0*
#10350
b1101000 <
1*
#10400
0*
#10450
b1101001 <
1*
#10500
0*
#10550
b1101010 <
1*
#10600
0*
#10650
b1101011 <
1*
#10700
0*
#10750
b1101100 <
1*
#10800
0*
#10850
b1101101 <
1*
#10900
0*
#10950
b1101110 <
1*
#11000
0*
#11050
b1101111 <
1*
#11100
0*
#11150
b1110000 <
1*
#11200
0*
#11250
b1110001 <
1*
#11300
0*
#11350
b1110010 <
1*
#11400
0*
#11450
b1110011 <
1*
#11500
0*
#11550
b1110100 <
1*
#11600
0*
#11650
b1110101 <
1*
#11700
0*
#11750
b1110110 <
1*
#11800
0*
#11850
b1110111 <
1*
#11900
0*
#11950
b1111000 <
1*
#12000
0*
#12050
b1111001 <
1*
#12100
0*
#12150
b1111010 <
1*
#12200
0*
#12250
b1111011 <
1*
#12300
0*
#12350
b1111100 <
1*
#12400
0*
#12450
b1111101 <
1*
#12500
0*
#12550
b1111110 <
1*
#12600
0*
#12650
b1111111 <
1*
#12700
0*
#12750
b10000000 <
1*
#12800
0*
#12850
b10000001 <
1*
#12900
0*
#12950
b10000010 <
1*
